Zrelay.py
zrelay-0.0.2.dist-info/LICENSE
zrelay-0.0.2.dist-info/METADATA
zrelay-0.0.2.dist-info/WHEEL
zrelay-0.0.2.dist-info/top_level.txt
zrelay-0.0.2.dist-info/RECORD
